finance/__init__.py
finance/covidresilient.py
finance/equityindex.py
FINANCEPP-1.3.3.dist-info/LICENSE
FINANCEPP-1.3.3.dist-info/METADATA
FINANCEPP-1.3.3.dist-info/WHEEL
FINANCEPP-1.3.3.dist-info/entry_points.txt
FINANCEPP-1.3.3.dist-info/top_level.txt
FINANCEPP-1.3.3.dist-info/RECORD
