Metadata-Version: 2.1
Name: FINANCEPP
Version: 1.3.3
Summary: Algorithm for finance
Home-page: UNKNOWN
License: MIT
Platform: UNKNOWN
Requires-Dist: pandas
Requires-Dist: numpy
Requires-Dist: datetime
Requires-Dist: pandas-datareader
